weboob/__init__.py
woob/__init__.py
woob/__main__.py
woob/exceptions.py
woob/launcher.py
woob/applications/__init__.py
woob/applications/bands/__init__.py
woob/applications/bands/bands.py
woob/applications/bank/__init__.py
woob/applications/bank/bank.py
woob/applications/bill/__init__.py
woob/applications/bill/bill.py
woob/applications/books/__init__.py
woob/applications/books/books.py
woob/applications/bugtracker/__init__.py
woob/applications/bugtracker/bugtracker.py
woob/applications/calendar/__init__.py
woob/applications/calendar/calendar.py
woob/applications/cinema/__init__.py
woob/applications/cinema/cinema.py
woob/applications/cli/__init__.py
woob/applications/cli/cli.py
woob/applications/config/__init__.py
woob/applications/config/config.py
woob/applications/contentedit/__init__.py
woob/applications/contentedit/contentedit.py
woob/applications/dating/__init__.py
woob/applications/dating/dating.py
woob/applications/debug/__init__.py
woob/applications/debug/debug.py
woob/applications/gallery/__init__.py
woob/applications/gallery/gallery.py
woob/applications/gauge/__init__.py
woob/applications/gauge/gauge.py
woob/applications/geolocip/__init__.py
woob/applications/geolocip/geolocip.py
woob/applications/housing/__init__.py
woob/applications/housing/housing.py
woob/applications/job/__init__.py
woob/applications/job/job.py
woob/applications/lyrics/__init__.py
woob/applications/lyrics/lyrics.py
woob/applications/main/__init__.py
woob/applications/money/__init__.py
woob/applications/money/money.py
woob/applications/msg/__init__.py
woob/applications/msg/msg.py
woob/applications/parcel/__init__.py
woob/applications/parcel/parcel.py
woob/applications/paste/__init__.py
woob/applications/paste/paste.py
woob/applications/pricecompare/__init__.py
woob/applications/pricecompare/pricecompare.py
woob/applications/radio/__init__.py
woob/applications/radio/radio.py
woob/applications/recipes/__init__.py
woob/applications/recipes/recipes.py
woob/applications/repos/__init__.py
woob-3.7.dist-info/AUTHORS
woob-3.7.dist-info/COPYING
woob-3.7.dist-info/COPYING.LESSER
woob-3.7.dist-info/METADATA
woob-3.7.dist-info/WHEEL
woob-3.7.dist-info/entry_points.txt
woob-3.7.dist-info/top_level.txt
woob-3.7.dist-info/RECORD
