Metadata-Version: 2.1
Name: woob
Version: 3.7
Summary: Woob, Web Outside Of Browsers
Author-email: Romain Bignon <romain@woob.dev>
License: LGPL-3.0-or-later
Project-URL: Homepage, https://woob.tech
Project-URL: Source, https://gitlab.com/woob/woob
Project-URL: Release notes, https://gitlab.com/woob/woob/-/releases
Project-URL: Documentation, https://woob.dev
Project-URL: Bug Tracker, https://gitlab.com/woob/woob/-/issues
Keywords: scraping,web,banking
Classifier: Environment :: Console
Classifier: License :: OSI Approved :: GNU Lesser General Public License v3 or later (LGPLv3+)
Classifier: Programming Language :: Python
Classifier: Programming Language :: Python :: 3
Classifier: Programming Language :: Python :: 3.7
Classifier: Programming Language :: Python :: 3.8
Classifier: Programming Language :: Python :: 3.9
Classifier: Programming Language :: Python :: 3.10
Classifier: Programming Language :: Python :: 3.11
Classifier: Programming Language :: Python
Classifier: Topic :: Internet :: WWW/HTTP
Classifier: Topic :: Internet :: WWW/HTTP :: Browsers
Classifier: Topic :: Software Development :: Libraries :: Application Frameworks
Classifier: Topic :: Software Development :: Libraries :: Python Modules
Classifier: Topic :: Text Processing :: Markup :: HTML
Requires-Python: >=3.7
License-File: COPYING
License-File: COPYING.LESSER
License-File: AUTHORS
Requires-Dist: lxml
Requires-Dist: requests!=2.32.0,!=2.32.1,!=2.32.2,!=2.32.3,>=2.0.0
Requires-Dist: python-dateutil
Requires-Dist: PyYAML
Requires-Dist: html2text>=3.200
Requires-Dist: unidecode
Requires-Dist: Pillow
Requires-Dist: Babel
Requires-Dist: packaging~=23.0
Requires-Dist: pycountry
Requires-Dist: rich~=13.0
Requires-Dist: termcolor
Requires-Dist: importlib-metadata~=6.7; python_version < "3.8"
